{
  "description": "WordPress自動投稿用のライバー向けテーマ・トピックリスト。SEO対策と求人獲得を目的とした記事生成に使用",
  "lastUpdated": "2026-01-14",
  "categories": {
    "beginner": {
      "name": "未経験者向け",
      "description": "ライバー未経験者の不安を解消し、始めるきっかけを提供",
      "topics": [
        {
          "title": "ライバーの始め方完全ガイド【未経験でも安心】",
          "keywords": ["ライバー 始め方", "ライバー 未経験", "ライバー なり方"],
          "targetAudience": "ライバーに興味はあるが始め方がわからない人",
          "angle": "ステップバイステップで解説、不安を払拭"
        },
        {
          "title": "ライバーは本当に稼げる？リアルな収入事情を解説",
          "keywords": ["ライバー 稼げる", "ライバー 収入", "ライバー 給料"],
          "targetAudience": "収入が気になる人",
          "angle": "Pocochaの時給制など具体的なデータを交えて"
        },
        {
          "title": "ライバーの仕事内容とは？1日の流れを詳しく解説",
          "keywords": ["ライバー 仕事内容", "ライバー 何する", "ライバーとは"],
          "targetAudience": "仕事内容が想像できない人",
          "angle": "具体的な配信フローで理解を促進"
        },
        {
          "title": "【初心者向け】ライバー事務所の選び方｜失敗しないポイント",
          "keywords": ["ライバー事務所 選び方", "ライバー事務所 おすすめ", "ライバー 所属"],
          "targetAudience": "事務所選びで迷っている人",
          "angle": "安全な事務所の見分け方を具体的に"
        },
        {
          "title": "ライバーに向いている人・向いていない人の特徴",
          "keywords": ["ライバー 向いてる人", "ライバー 適性", "ライバー 性格"],
          "targetAudience": "自分に合うか不安な人",
          "angle": "具体的なタイプ別で解説"
        }
      ]
    },
    "income": {
      "name": "収入・稼ぎ方",
      "description": "具体的な収入情報と稼ぐためのノウハウ",
      "topics": [
        {
          "title": "ライバーで月収30万円稼ぐための具体的な方法",
          "keywords": ["ライバー 月収30万", "ライバー 高収入", "ライバー 稼ぐコツ"],
          "targetAudience": "しっかり稼ぎたい人",
          "angle": "具体的な配信時間と戦略を提示"
        },
        {
          "title": "Pocochaの時給制を徹底解説｜ランク別の報酬額",
          "keywords": ["Pococha 時給", "Pococha 報酬", "Pococha ランク"],
          "targetAudience": "Pocochaに興味がある人",
          "angle": "D1〜S6までのランク別時給を具体的に"
        },
        {
          "title": "17LIVE vs Pococha vs IRIAM｜稼げるアプリを徹底比較",
          "keywords": ["17LIVE 稼げる", "ライブ配信アプリ 比較", "Pococha IRIAM"],
          "targetAudience": "アプリ選びで迷っている人",
          "angle": "各プラットフォームの特徴と報酬を比較"
        },
        {
          "title": "【体験談】副業ライバーで月15万円稼いだ方法",
          "keywords": ["ライバー 副業", "ライバー 週末", "副業 ライブ配信"],
          "targetAudience": "本業がある人",
          "angle": "リアルな体験ベースで信頼性向上"
        },
        {
          "title": "ライバーで稼げない人の特徴5選｜改善方法も解説",
          "keywords": ["ライバー 稼げない", "ライバー うまくいかない", "ライバー コツ"],
          "targetAudience": "すでに始めているが稼げていない人",
          "angle": "問題解決型コンテンツ"
        }
      ]
    },
    "safety": {
      "name": "安全・身バレ対策",
      "description": "最大の懸念である身バレ・安全面の不安を解消",
      "topics": [
        {
          "title": "ライバーの身バレ対策完全マニュアル【安心して配信】",
          "keywords": ["ライバー 身バレ", "ライバー バレない", "配信 身バレ対策"],
          "targetAudience": "身バレを心配している人",
          "angle": "具体的な対策方法を網羅"
        },
        {
          "title": "顔出しなしでライバーはできる？稼げる？IRIAM・REALITYを解説",
          "keywords": ["ライバー 顔出しなし", "Vライバー 稼げる", "IRIAM REALITY"],
          "targetAudience": "顔出しに抵抗がある人",
          "angle": "Vtuber系アプリでの活動方法"
        },
        {
          "title": "ライバーは親・彼氏・会社にバレる？バレない方法を解説",
          "keywords": ["ライバー 親バレ", "ライバー 彼氏", "ライバー 会社バレ"],
          "targetAudience": "周囲にバレることを心配している人",
          "angle": "ケース別の対策を提示"
        },
        {
          "title": "ライバーの確定申告と税金｜副業がバレない方法",
          "keywords": ["ライバー 確定申告", "ライバー 税金", "ライバー 副業バレ"],
          "targetAudience": "税金面で不安がある人",
          "angle": "具体的な手続きを解説"
        },
        {
          "title": "ライバー活動のリスクと対策｜安全に続けるために",
          "keywords": ["ライバー リスク", "ライバー 危険", "ライバー 安全"],
          "targetAudience": "安全面に不安がある人",
          "angle": "リスクと対策を正直に解説"
        }
      ]
    },
    "skills": {
      "name": "スキルアップ・テクニック",
      "description": "稼ぐための具体的なテクニックとスキル",
      "topics": [
        {
          "title": "ライバーのトーク術｜リスナーを惹きつける7つのテクニック",
          "keywords": ["ライバー トーク", "ライバー 会話", "配信 話し方"],
          "targetAudience": "トーク力を上げたい人",
          "angle": "すぐに使える具体的なテクニック"
        },
        {
          "title": "ライバーのプロフィール作成術｜ファンを増やす書き方",
          "keywords": ["ライバー プロフィール", "配信 自己紹介", "Pococha プロフィール"],
          "targetAudience": "プロフィールを改善したい人",
          "angle": "例文付きで実践的に"
        },
        {
          "title": "ライバーの配信機材おすすめ｜初心者向け照明・マイク選び",
          "keywords": ["ライバー 機材", "配信 照明", "配信 マイク おすすめ"],
          "targetAudience": "機材を揃えたい人",
          "angle": "具体的なおすすめ商品も紹介"
        },
        {
          "title": "ライバーの稼げる時間帯は？効率的に稼ぐ配信戦略",
          "keywords": ["ライバー 時間帯", "配信 ゴールデンタイム", "ライバー 効率"],
          "targetAudience": "効率的に稼ぎたい人",
          "angle": "データに基づいた時間帯分析"
        },
        {
          "title": "Pocochaのランクアップ攻略法｜S帯を目指す戦略",
          "keywords": ["Pococha ランク上げ", "Pococha 攻略", "Pococha S帯"],
          "targetAudience": "Pocochaで上を目指す人",
          "angle": "具体的なランクアップ戦略"
        }
      ]
    },
    "lifestyle": {
      "name": "ライフスタイル・働き方",
      "description": "様々な境遇の人に向けた働き方提案",
      "topics": [
        {
          "title": "子育て中でもできる！主婦・ママにおすすめのライバー活動",
          "keywords": ["ライバー 主婦", "ライバー ママ", "ライバー 子育て"],
          "targetAudience": "子育て中の女性",
          "angle": "両立のコツと成功事例"
        },
        {
          "title": "大学生がライバーで稼ぐ方法｜学業との両立術",
          "keywords": ["ライバー 大学生", "ライバー 学生", "学生 ライブ配信"],
          "targetAudience": "大学生",
          "angle": "学生ならではの強みを活かす"
        },
        {
          "title": "30代・40代から始めるライバー｜年齢は強みになる",
          "keywords": ["ライバー 30代", "ライバー 40代", "ライバー 年齢"],
          "targetAudience": "30代以上の女性",
          "angle": "年齢層別の需要と戦略を解説"
        },
        {
          "title": "会社員がライバーを副業にするメリットと注意点",
          "keywords": ["ライバー 副業 会社員", "ライバー 副業 バレない", "副業 ライブ配信"],
          "targetAudience": "会社員",
          "angle": "副業としての始め方と注意点"
        },
        {
          "title": "スマホだけでライバーはできる？スマホ配信のコツ",
          "keywords": ["ライバー スマホ", "ライブ配信 スマホ", "配信 スマホだけ"],
          "targetAudience": "PC環境がない人",
          "angle": "スマホでの始め方を詳しく"
        }
      ]
    },
    "platform": {
      "name": "プラットフォーム別ガイド",
      "description": "各配信プラットフォームの詳細解説",
      "topics": [
        {
          "title": "Pococha完全ガイド｜始め方から稼ぎ方まで徹底解説",
          "keywords": ["Pococha 始め方", "Pococha 稼ぎ方", "Pococha 初心者"],
          "targetAudience": "Pococha初心者",
          "angle": "Pocochaに特化した網羅的ガイド"
        },
        {
          "title": "17LIVE（イチナナ）の特徴と稼ぎ方｜投げ銭で稼ぐコツ",
          "keywords": ["17LIVE 稼ぎ方", "イチナナ 始め方", "17LIVE 投げ銭"],
          "targetAudience": "17LIVEに興味がある人",
          "angle": "投げ銭システムとイベント攻略"
        },
        {
          "title": "IRIAM完全ガイド｜イラスト1枚で始めるVライバー",
          "keywords": ["IRIAM 始め方", "IRIAM 稼げる", "Vライバー IRIAM"],
          "targetAudience": "Vライバーに興味がある人",
          "angle": "顔出しなしでの活動方法"
        },
        {
          "title": "REALITY完全ガイド｜アバターで始めるライブ配信",
          "keywords": ["REALITY 始め方", "REALITY 稼げる", "REALITY 配信"],
          "targetAudience": "REALITYに興味がある人",
          "angle": "アバター配信の特徴と戦略"
        },
        {
          "title": "TikTokライブで稼ぐ方法｜フォロワー0からの始め方",
          "keywords": ["TikTokライブ 稼ぐ", "TikTok 配信 始め方", "TikTok 収益化"],
          "targetAudience": "TikTokユーザー",
          "angle": "TikTokからの流入と収益化"
        }
      ]
    },
    "trends": {
      "name": "トレンド・最新情報",
      "description": "業界の最新動向",
      "topics": [
        {
          "title": "【2026年最新】ライバー業界の動向と将来性",
          "keywords": ["ライバー 将来性", "ライブ配信 市場", "ライバー トレンド"],
          "targetAudience": "業界動向を知りたい人",
          "angle": "市場データを元に分析"
        },
        {
          "title": "VTuber・Vライバーの最新トレンド｜顔出しなしで稼ぐ時代",
          "keywords": ["VTuber トレンド", "Vライバー 稼ぐ", "アバター配信"],
          "targetAudience": "顔出しせずに稼ぎたい人",
          "angle": "最新トレンドを詳しく解説"
        },
        {
          "title": "AIとライバー配信の融合｜新しい配信スタイルとは",
          "keywords": ["ライバー AI", "配信 AI活用", "ライブ配信 最新"],
          "targetAudience": "新技術に興味がある人",
          "angle": "最新技術の活用方法"
        }
      ]
    },
    "qa": {
      "name": "Q&A・よくある質問",
      "description": "疑問解消型コンテンツ",
      "topics": [
        {
          "title": "ライバーのよくある質問50選｜始める前に知っておきたいこと",
          "keywords": ["ライバー 質問", "ライバー FAQ", "ライバー 疑問"],
          "targetAudience": "様々な疑問がある人",
          "angle": "網羅的にQ&A形式で"
        },
        {
          "title": "ライバーを辞めたい時の対処法｜事務所の退所方法",
          "keywords": ["ライバー 辞めたい", "ライバー 退所", "ライバー やめ方"],
          "targetAudience": "退所を検討している人",
          "angle": "スムーズな辞め方を解説"
        },
        {
          "title": "ライバーで嫌なリスナーへの対処法｜トラブル対応マニュアル",
          "keywords": ["ライバー トラブル", "配信 荒らし", "リスナー 対応"],
          "targetAudience": "トラブル対応を知りたい人",
          "angle": "具体的な対処法を例示"
        }
      ]
    }
  },
  "seoKeywords": {
    "highVolume": [
      "ライバー",
      "ライバー 稼ぐ",
      "ライバー 始め方",
      "Pococha 稼げる",
      "ライブ配信 稼ぐ",
      "17LIVE 始め方"
    ],
    "mediumVolume": [
      "ライバー 未経験",
      "ライバー 顔出しなし",
      "ライバー 事務所",
      "ライバー 時給",
      "Vライバー 稼げる",
      "IRIAM 始め方"
    ],
    "longTail": [
      "ライバー 主婦 在宅",
      "ライバー 大学生 バイト",
      "ライバー 30代 始める",
      "ライバー 副業 バレない",
      "Pococha ランク上げ方"
    ]
  },
  "contentCalendar": {
    "weeklyRotation": [
      { "week": 1, "focus": "未経験者向け・始め方系" },
      { "week": 2, "focus": "収入・稼ぎ方系" },
      { "week": 3, "focus": "プラットフォーム別ガイド" },
      { "week": 4, "focus": "スキルアップ・テクニック系" }
    ],
    "seasonalTopics": {
      "1月": "新年・新しい挑戦",
      "3月": "卒業・新生活準備",
      "4月": "新生活・副業開始",
      "8月": "夏休み・学生向け",
      "12月": "年末・副収入"
    }
  }
}
